beaker_climate/__about__.py
beaker_climate/__init__.py
beaker_climate/climate_python/README.md
beaker_climate/climate_python/__init__.py
beaker_climate/climate_python/agent.py
beaker_climate/climate_python/context.py
beaker_climate/climate_python/api_documentation/esgf_documentation.md
beaker_climate/climate_python/api_documentation/esgf_rest_documentation.md
beaker_climate/climate_python/procedures/python3/flowcast_regridding.py
beaker_climate/climate_python/procedures/python3/get_netcdf_plot.py
beaker_climate/climate_python/utils/check_gemini_cache.py
beaker_climate/climate_python/utils/esgf_docs.py
beaker_climate/mimi_modeling/README.md
beaker_climate/mimi_modeling/__init__.py
beaker_climate/mimi_modeling/agent.py
beaker_climate/mimi_modeling/api_agent.yaml
beaker_climate/mimi_modeling/context.py
beaker_climate/mimi_modeling/default_payload.json
beaker_climate/mimi_modeling/yaml_loader.py
beaker_climate/mimi_modeling/api_definitions/loader-workflow.png
beaker_climate/mimi_modeling/api_definitions/readme.md
beaker_climate/mimi_modeling/api_definitions/mimifund/api.yaml
beaker_climate/mimi_modeling/api_definitions/mimifund/documentation/components.md
beaker_climate/mimi_modeling/api_definitions/mimifund/documentation/mimi.md
beaker_climate/mimi_modeling/api_definitions/mimifund/documentation/mimi_existing_model.md
beaker_climate/mimi_modeling/api_definitions/mimifund/documentation/mimi_modification.md
beaker_climate/mimi_modeling/api_definitions/mimifund/documentation/parameters.md
beaker_climate/mimi_modeling/api_definitions/mimifund/documentation/readme.md
beaker_climate/mimi_modeling/api_definitions/mimifund/documentation/science.md
beaker_climate/mimi_modeling/api_definitions/mimifund/documentation/tables.md
beaker_climate/mimi_modeling/procedures/python3/.keep
beaker_climate-0.0.1.data/data/share/beaker/contexts/beaker_climate.json
beaker_climate-0.0.1.data/data/share/beaker/contexts/mimi_modeling.json
beaker_climate-0.0.1.dist-info/METADATA
beaker_climate-0.0.1.dist-info/WHEEL
beaker_climate-0.0.1.dist-info/licenses/LICENSE.txt
beaker_climate-0.0.1.dist-info/RECORD
